MANIFEST.in
README.rst
requirements-tests.txt
requirements.txt
setup.py
newsboard/__init__.py
newsboard/apps.py
newsboard/functional_tests.py
newsboard/log.py
newsboard/models.py
newsboard/periodic_tasks.py
newsboard/settings.py
newsboard/tag_backends.py
newsboard/tasks.py
newsboard/urls.py
newsboard/views.py
newsboard.egg-info/PKG-INFO
newsboard.egg-info/SOURCES.txt
newsboard.egg-info/dependency_links.txt
newsboard.egg-info/not-zip-safe
newsboard.egg-info/requires.txt
newsboard.egg-info/top_level.txt
newsboard/admin/__init__.py
newsboard/admin/forms.py
newsboard/admin/modeladmins.py
newsboard/contrib/__init__.py
newsboard/contrib/filters.py
newsboard/feeds/__init__.py
newsboard/feeds/base.py
newsboard/feeds/facebookfeed.py
newsboard/feeds/rss.py
newsboard/feeds/sitemap.py
newsboard/management/__init__.py
newsboard/management/commands/__init__.py
newsboard/management/commands/update_streams.py
newsboard/migrations/0001_initial.py
newsboard/migrations/0002_auto_20190913_0018.py
newsboard/migrations/0003_profile_tag.py
newsboard/migrations/__init__.py
newsboard/templates/newsboard/_post.html
newsboard/templates/newsboard/_posts.html
newsboard/templates/newsboard/base.html
newsboard/templates/newsboard/post.html
newsboard/templates/newsboard/posts.html
newsboard/templates/newsboard/stream.html
newsboard/templates/newsboard/streams.html
newsboard/tests/__init__.py
newsboard/tests/celery.py
newsboard/tests/factories.py
newsboard/tests/settings.py
newsboard/tests/test_models.py
newsboard/tests/test_tasks.py
newsboard/tests/urls.py
newsboard/tests/utils.py