Metadata-Version: 1.1
Name: newsboard
Version: 0.2.1
Summary: Gather many feeds in one
Home-page: https://github.com/ZuluPro/newsboard
Author: Anthony Monthe (ZuluPro)
Author-email: anthony.monthe@gmail.com
License: BSD
Keywords: web,django,opengraph,web-rich-object,facebook,rss,sitemap
Platform: UNKNOWN
Classifier: Framework :: Django
Classifier: Development Status :: 5 - Production/Stable
Classifier: Environment :: Web Environment
Classifier: Programming Language :: Python
Classifier: Programming Language :: Python :: 3
Classifier: Intended Audience :: Developers
Classifier: Operating System :: OS Independent
Classifier: License :: OSI Approved :: BSD License
Classifier: Topic :: Software Development :: Libraries :: Python Modules
